etc/monasca/events-api-logging.conf
etc/monasca/events-api-paste.ini
monasca_events_api/__init__.py
monasca_events_api/config.py
monasca_events_api/version.py
monasca_events_api/app/__init__.py
monasca_events_api/app/api.py
monasca_events_api/app/wsgi.py
monasca_events_api/app/common/__init__.py
monasca_events_api/app/common/events_publisher.py
monasca_events_api/app/common/helpers.py
monasca_events_api/app/controller/__init__.py
monasca_events_api/app/controller/healthchecks.py
monasca_events_api/app/controller/versions.py
monasca_events_api/app/controller/api/__init__.py
monasca_events_api/app/controller/v1/__init__.py
monasca_events_api/app/controller/v1/body_validation.py
monasca_events_api/app/controller/v1/bulk_processor.py
monasca_events_api/app/controller/v1/events.py
monasca_events_api/app/core/__init__.py
monasca_events_api/app/core/error_handlers.py
monasca_events_api/app/core/model.py
monasca_events_api/app/core/request.py
monasca_events_api/app/core/request_contex.py
monasca_events_api/app/core/validation.py
monasca_events_api/app/healthcheck/__init__.py
monasca_events_api/app/healthcheck/kafka_check.py
monasca_events_api/app/model/__init__.py
monasca_events_api/app/model/envelope.py
monasca_events_api/conf/__init__.py
monasca_events_api/conf/events_publisher.py
monasca_events_api/policies/__init__.py
monasca_events_api/policies/admin.py
monasca_events_api/policies/agent.py
monasca_events_api/tests/__init__.py
monasca_events_api/tests/functional/__init__.py
monasca_events_api/tests/functional/contrib/gate_hook.sh
monasca_events_api/tests/functional/contrib/post_test_hook.sh
monasca_events_api/tests/unit/__init__.py
monasca_events_api/tests/unit/base.py
monasca_events_api/tests/unit/test_body_validation.py
monasca_events_api/tests/unit/test_events_v1.py
monasca_events_api/tests/unit/test_healthchecks.py
monasca_events_api/tests/unit/test_policy.py
monasca_events_api/tests/unit/test_request.py
monasca_events_api/tests/unit/test_versions.py
monasca_events_api-8.0.0.dist-info/AUTHORS
monasca_events_api-8.0.0.dist-info/LICENSE
monasca_events_api-8.0.0.dist-info/METADATA
monasca_events_api-8.0.0.dist-info/WHEEL
monasca_events_api-8.0.0.dist-info/entry_points.txt
monasca_events_api-8.0.0.dist-info/pbr.json
monasca_events_api-8.0.0.dist-info/top_level.txt
monasca_events_api-8.0.0.dist-info/RECORD
