Metadata-Version: 2.1
Name: monasca-events-api
Version: 8.0.0
Summary: Monasca API for events
Home-page: https://github.com/openstack/monasca-events-api
Author: OpenStack
Author-email: openstack-discuss@lists.openstack.org
License: UNKNOWN
Platform: UNKNOWN
Classifier: Environment :: OpenStack
Classifier: Intended Audience :: Information Technology
Classifier: Intended Audience :: System Administrators
Classifier: License :: OSI Approved :: Apache Software License
Classifier: Operating System :: POSIX :: Linux
Classifier: Programming Language :: Python
Classifier: Programming Language :: Python :: 3
Classifier: Programming Language :: Python :: 3.6
Classifier: Programming Language :: Python :: 3.7
Requires-Dist: Paste (>=2.0.2)
Requires-Dist: PasteDeploy (>=1.5.0)
Requires-Dist: eventlet (!=0.18.3,!=0.20.1,>=0.18.2)
Requires-Dist: falcon (>=2.0.0)
Requires-Dist: keystonemiddleware (>=4.12.0)
Requires-Dist: monasca-common (>=1.4.0)
Requires-Dist: oslo.config (>=6.1.0)
Requires-Dist: oslo.context (>=2.14.0)
Requires-Dist: oslo.log (>=3.22.0)
Requires-Dist: oslo.middleware (>=3.27.0)
Requires-Dist: oslo.policy (>=1.23.0)
Requires-Dist: oslo.serialization (!=2.19.1,>=1.10.0)
Requires-Dist: oslo.utils (>=3.20.0)
Requires-Dist: pbr (!=2.1.0,>=2.0.0)
Requires-Dist: six (>=1.10.0)
Requires-Dist: voluptuous (>=0.8.9)
